cegalprizm/investigator/__init__.py
cegalprizm/investigator/config.py
cegalprizm/investigator/connection.py
cegalprizm/investigator/constants.py
cegalprizm/investigator/decorators.py
cegalprizm/investigator/exceptions.py
cegalprizm/investigator/from_dataframe.py
cegalprizm/investigator/hub_context.py
cegalprizm/investigator/investigations.py
cegalprizm/investigator/iris.py
cegalprizm/investigator/named_tuples.py
cegalprizm/investigator/petrel.py
cegalprizm/investigator/pickling.py
cegalprizm/investigator/plotting.py
cegalprizm/investigator/statistics.py
cegalprizm/investigator/utils.py
cegalprizm/investigator/utils_investigation.py
cegalprizm/investigator/utils_pythontoolpro.py
cegalprizm/investigator/inv/continuous_dimension.py
cegalprizm/investigator/inv/dataset.py
cegalprizm/investigator/inv/discrete_dimension.py
cegalprizm/investigator/inv/intersections.py
cegalprizm/investigator/inv/investigation.py
cegalprizm/investigator/inv/models.py
cegalprizm/investigator/inv/refresh.py
cegalprizm/investigator/inv/to_dataframe.py
cegalprizm/investigator/inv/update.py
cegalprizm/investigator/protos/common_pb2.py
cegalprizm/investigator/protos/investigation_pb2.py
cegalprizm/investigator/protos/investigator_api_pb2.py
cegalprizm/investigator/protos/petrel_pb2.py
cegalprizm/investigator/protos/predefined_view_pb2.py
cegalprizm/investigator/protos/web_pb2.py
cegalprizm/investigator/views/__init__.py
cegalprizm/investigator/views/base_legend.py
cegalprizm/investigator/views/crossplot.py
cegalprizm/investigator/views/histogram.py
cegalprizm/investigator/views/investigator_window_predefined_view.py
cegalprizm/investigator/views/logtracks.py
cegalprizm/investigator/views/map.py
cegalprizm/investigator/views/matrix.py
cegalprizm/investigator/views/model_intersection.py
cegalprizm/investigator/views/options_colorscale.py
cegalprizm/investigator/views/options_histograms.py
cegalprizm/investigator/views/options_legend.py
cegalprizm/investigator/views/options_scatterplot.py
cegalprizm_investigator-1.4.0.dist-info/LICENSE
cegalprizm_investigator-1.4.0.dist-info/METADATA
cegalprizm_investigator-1.4.0.dist-info/WHEEL
cegalprizm_investigator-1.4.0.dist-info/top_level.txt
cegalprizm_investigator-1.4.0.dist-info/RECORD
