Metadata-Version: 2.1
Name: cegalprizm-investigator
Version: 1.4.0
Summary: Cegal Prizm Investigator
Home-page: https://docs.prizm.cegal-geo.com/
Author: Cegal Prizm Team
Author-email: prizm@cegal.com
Classifier: Programming Language :: Python :: 3
Classifier: License :: Other/Proprietary License
Classifier: Operating System :: OS Independent
Requires-Python: >=3.6
License-File: LICENSE
Requires-Dist: grpcio
Requires-Dist: protobuf
Requires-Dist: pandas
Requires-Dist: cloudpickle
Requires-Dist: pillow
Requires-Dist: webcolors
Requires-Dist: cegal-keystoneauth <2,>=1
Requires-Dist: cegalprizm-hub <2,>=1.2.2
